sstools/__init__.py
sstools/fina_base_times.pkl
sstools/rudolph_points_table.xls
sstools/rudolph_punkttabelle.pkl
sstools/ssconv.py
tests/__init__.py
tests/test_ssconv.py
sstools-0.2.9.dist-info/METADATA
sstools-0.2.9.dist-info/WHEEL
sstools-0.2.9.dist-info/top_level.txt
sstools-0.2.9.dist-info/RECORD
