Metadata-Version: 2.1
Name: sstools
Version: 0.2.9
Summary: swimstats tools
Home-page: https://swimstats.net
Author: Roman Arnet
Author-email: arnet@dlab.ch
Classifier: Programming Language :: Python :: 3
Classifier: License :: OSI Approved :: MIT License
Classifier: Operating System :: OS Independent
Requires-Python: >=3.6
